{
  "id": "puerto-quetzal-301a-gtm-uhslc-rq",
  "name": "puerto_quetzal-301a-gtm-uhslc_rq",
  "continent": "Americas",
  "country": "Guatemala",
  "latitude": 13.922,
  "longitude": -90.785,
  "type": "reference",
  "timezone": "America/Guatemala",
  "disclaimers": "No obvious issues",
  "source": {
    "name": "TICON-4",
    "url": "https://www.seanoe.org/data/00980/109129/",
    "id": "puerto_quetzal-301a-gtm-uhslc_rq",
    "datum": "Unspecified",
    "observation_period": {
      "start": "22/11/1983",
      "end": "06/10/1986",
      "years": 4
    }
  },
  "license": {
    "name": "cc-by-4.0",
    "url": "https://creativecommons.org/licenses/by/4.0/"
  },
  "harmonic_constituents": [
    {
      "name": "M2",
      "amplitude": 67.272128,
      "phase_UTC": -121.077918
    },
    {
      "name": "N2",
      "amplitude": 12.632173,
      "phase_UTC": -150.149888
    },
    {
      "name": "S2",
      "amplitude": 12.768672,
      "phase_UTC": -49.903136
    },
    {
      "name": "K2",
      "amplitude": 3.099246,
      "phase_UTC": -64.758449
    },
    {
      "name": "2N2",
      "amplitude": 0.493941,
      "phase_UTC": -146.351848
    },
    {
      "name": "S1",
      "amplitude": 1.809816,
      "phase_UTC": -175.343754
    },
    {
      "name": "K1",
      "amplitude": 9.537722,
      "phase_UTC": 95.013974
    },
    {
      "name": "P1",
      "amplitude": 3.070436,
      "phase_UTC": 98.986526
    },
    {
      "name": "O1",
      "amplitude": 5.361023,
      "phase_UTC": 121.515483
    },
    {
      "name": "Q1",
      "amplitude": 1.327603,
      "phase_UTC": 133.111132
    },
    {
      "name": "M1",
      "amplitude": 0.533766,
      "phase_UTC": 1.5334
    },
    {
      "name": "M4",
      "amplitude": 0.526477,
      "phase_UTC": 22.289508
    },
    {
      "name": "MM",
      "amplitude": 0.74153,
      "phase_UTC": 19.935072
    },
    {
      "name": "MF",
      "amplitude": 1.117465,
      "phase_UTC": 45.639441
    },
    {
      "name": "SA",
      "amplitude": 7.951168,
      "phase_UTC": 137.64038
    },
    {
      "name": "SSA",
      "amplitude": 2.524917,
      "phase_UTC": -175.609041
    },
    {
      "name": "T2",
      "amplitude": 2.250666,
      "phase_UTC": -98.524602
    },
    {
      "name": "J1",
      "amplitude": 0.931473,
      "phase_UTC": 106.440778
    },
    {
      "name": "L2",
      "amplitude": 0.648326,
      "phase_UTC": -143.851834
    },
    {
      "name": "R2",
      "amplitude": 0.227759,
      "phase_UTC": -37.13336
    },
    {
      "name": "2Q1",
      "amplitude": 0.127134,
      "phase_UTC": 70.003196
    },
    {
      "name": "MSF",
      "amplitude": 0.282538,
      "phase_UTC": -68.564295
    },
    {
      "name": "MSQM",
      "amplitude": 0.273153,
      "phase_UTC": -70.431245
    },
    {
      "name": "EP2",
      "amplitude": 0.632498,
      "phase_UTC": 127.269361
    },
    {
      "name": "M3",
      "amplitude": 0.161435,
      "phase_UTC": -176.588882
    },
    {
      "name": "MU2",
      "amplitude": 3.135418,
      "phase_UTC": 168.753752
    },
    {
      "name": "MTM",
      "amplitude": 0.384094,
      "phase_UTC": 22.034529
    },
    {
      "name": "NU2",
      "amplitude": 3.985067,
      "phase_UTC": 177.46543
    },
    {
      "name": "LAMBDA2",
      "amplitude": 2.472769,
      "phase_UTC": -43.936789
    },
    {
      "name": "MN4",
      "amplitude": 0.222375,
      "phase_UTC": 23.38077
    },
    {
      "name": "MS4",
      "amplitude": 0.104727,
      "phase_UTC": -172.667057
    },
    {
      "name": "MKS2",
      "amplitude": 2.281909,
      "phase_UTC": 170.783718
    },
    {
      "name": "N4",
      "amplitude": 0.085182,
      "phase_UTC": -19.125196
    },
    {
      "name": "M6",
      "amplitude": 0.61578,
      "phase_UTC": -11.107478
    },
    {
      "name": "M8",
      "amplitude": 0.043315,
      "phase_UTC": 64.415447
    },
    {
      "name": "S4",
      "amplitude": 0.054532,
      "phase_UTC": 28.973522
    },
    {
      "name": "OO1",
      "amplitude": 1.052194,
      "phase_UTC": 122.311335
    },
    {
      "name": "S3",
      "amplitude": 0.059734,
      "phase_UTC": -117.731019
    },
    {
      "name": "MA2",
      "amplitude": 9.814207,
      "phase_UTC": -121.115429
    },
    {
      "name": "MB2",
      "amplitude": 8.895481,
      "phase_UTC": 66.683599
    },
    {
      "name": "T3",
      "amplitude": 0.291882,
      "phase_UTC": -57.737767
    },
    {
      "name": "R3",
      "amplitude": 0.209555,
      "phase_UTC": 97.231986
    },
    {
      "name": "RHO1",
      "amplitude": 0.305506,
      "phase_UTC": 54.442463
    },
    {
      "name": "SGM",
      "amplitude": 0.190159,
      "phase_UTC": -106.17008
    },
    {
      "name": "3L2",
      "amplitude": 1.435682,
      "phase_UTC": 9.847595
    },
    {
      "name": "3N2",
      "amplitude": 0.533085,
      "phase_UTC": -71.359643
    },
    {
      "name": "2SM2",
      "amplitude": 0.200584,
      "phase_UTC": 79.712475
    },
    {
      "name": "2MS6",
      "amplitude": 0.282622,
      "phase_UTC": 63.857349
    },
    {
      "name": "2MK5",
      "amplitude": 0.122789,
      "phase_UTC": 112.900082
    },
    {
      "name": "2MO5",
      "amplitude": 0.028107,
      "phase_UTC": 156.702735
    }
  ],
  "secondary_offset": null
}
