{
  "id": "puntarenas-396a-cri-uhslc-rq",
  "name": "puntarenas-396a-cri-uhslc_rq",
  "continent": "Americas",
  "country": "Costa Rica",
  "latitude": 9.967,
  "longitude": -84.833,
  "type": "reference",
  "timezone": "America/Costa_Rica",
  "disclaimers": "No obvious issues",
  "source": {
    "name": "TICON-4",
    "url": "https://www.seanoe.org/data/00980/109129/",
    "id": "puntarenas-396a-cri-uhslc_rq",
    "datum": "Unspecified",
    "observation_period": {
      "start": "01/01/1961",
      "end": "31/12/1980",
      "years": 20
    }
  },
  "license": {
    "name": "cc-by-4.0",
    "url": "https://creativecommons.org/licenses/by/4.0/"
  },
  "harmonic_constituents": [
    {
      "name": "M2",
      "amplitude": 109.552506,
      "phase_UTC": -113.664305
    },
    {
      "name": "N2",
      "amplitude": 23.5502,
      "phase_UTC": -146.254339
    },
    {
      "name": "S2",
      "amplitude": 25.990942,
      "phase_UTC": -53.170709
    },
    {
      "name": "K2",
      "amplitude": 6.701105,
      "phase_UTC": -59.685559
    },
    {
      "name": "2N2",
      "amplitude": 3.008647,
      "phase_UTC": -177.623523
    },
    {
      "name": "S1",
      "amplitude": 0.930345,
      "phase_UTC": 165.393296
    },
    {
      "name": "K1",
      "amplitude": 10.470535,
      "phase_UTC": 74.67462
    },
    {
      "name": "P1",
      "amplitude": 3.16499,
      "phase_UTC": 74.248864
    },
    {
      "name": "O1",
      "amplitude": 3.858035,
      "phase_UTC": 103.861845
    },
    {
      "name": "Q1",
      "amplitude": 0.874024,
      "phase_UTC": 132.954195
    },
    {
      "name": "M1",
      "amplitude": 0.330762,
      "phase_UTC": -14.7076
    },
    {
      "name": "M4",
      "amplitude": 1.805866,
      "phase_UTC": -168.897012
    },
    {
      "name": "MM",
      "amplitude": 0.381086,
      "phase_UTC": -30.891496
    },
    {
      "name": "MF",
      "amplitude": 1.015551,
      "phase_UTC": 11.039901
    },
    {
      "name": "SA",
      "amplitude": 3.980484,
      "phase_UTC": 171.348027
    },
    {
      "name": "SSA",
      "amplitude": 3.182598,
      "phase_UTC": 172.615136
    },
    {
      "name": "T2",
      "amplitude": 1.680107,
      "phase_UTC": -46.352004
    },
    {
      "name": "J1",
      "amplitude": 0.80462,
      "phase_UTC": 88.236251
    },
    {
      "name": "L2",
      "amplitude": 2.393101,
      "phase_UTC": -87.7752
    },
    {
      "name": "R2",
      "amplitude": 0.123089,
      "phase_UTC": -84.652696
    },
    {
      "name": "2Q1",
      "amplitude": 0.176485,
      "phase_UTC": 131.867274
    },
    {
      "name": "MSF",
      "amplitude": 0.703203,
      "phase_UTC": -92.41078
    },
    {
      "name": "MSQM",
      "amplitude": 0.225947,
      "phase_UTC": -13.265119
    },
    {
      "name": "EP2",
      "amplitude": 1.022385,
      "phase_UTC": 166.389556
    },
    {
      "name": "M3",
      "amplitude": 0.321222,
      "phase_UTC": 45.729453
    },
    {
      "name": "MU2",
      "amplitude": 3.971953,
      "phase_UTC": -169.669406
    },
    {
      "name": "MTM",
      "amplitude": 0.125232,
      "phase_UTC": 77.703706
    },
    {
      "name": "NU2",
      "amplitude": 4.480131,
      "phase_UTC": -143.258453
    },
    {
      "name": "LAMBDA2",
      "amplitude": 0.59756,
      "phase_UTC": -88.107652
    },
    {
      "name": "MN4",
      "amplitude": 0.822748,
      "phase_UTC": 163.39018
    },
    {
      "name": "MS4",
      "amplitude": 0.874687,
      "phase_UTC": -98.659714
    },
    {
      "name": "MKS2",
      "amplitude": 0.451584,
      "phase_UTC": -105.344593
    },
    {
      "name": "N4",
      "amplitude": 0.191231,
      "phase_UTC": 124.912986
    },
    {
      "name": "M6",
      "amplitude": 0.172269,
      "phase_UTC": 138.189654
    },
    {
      "name": "M8",
      "amplitude": 0.140193,
      "phase_UTC": -177.735769
    },
    {
      "name": "S4",
      "amplitude": 0.182803,
      "phase_UTC": -33.739668
    },
    {
      "name": "OO1",
      "amplitude": 0.615115,
      "phase_UTC": 98.09658
    },
    {
      "name": "S3",
      "amplitude": 0.249325,
      "phase_UTC": 93.54302
    },
    {
      "name": "MA2",
      "amplitude": 0.094972,
      "phase_UTC": -13.407728
    },
    {
      "name": "MB2",
      "amplitude": 0.258383,
      "phase_UTC": 154.965287
    },
    {
      "name": "T3",
      "amplitude": 0.377213,
      "phase_UTC": -102.498697
    },
    {
      "name": "R3",
      "amplitude": 0.432745,
      "phase_UTC": 82.093928
    },
    {
      "name": "RHO1",
      "amplitude": 0.173054,
      "phase_UTC": 126.233284
    },
    {
      "name": "SGM",
      "amplitude": 0.122558,
      "phase_UTC": -43.172356
    },
    {
      "name": "3L2",
      "amplitude": 0.831506,
      "phase_UTC": -62.259748
    },
    {
      "name": "3N2",
      "amplitude": 0.496932,
      "phase_UTC": -129.883459
    },
    {
      "name": "2SM2",
      "amplitude": 0.079509,
      "phase_UTC": -160.376435
    },
    {
      "name": "2MS6",
      "amplitude": 0.258995,
      "phase_UTC": -163.068607
    },
    {
      "name": "2MK5",
      "amplitude": 0.012728,
      "phase_UTC": 6.233242
    },
    {
      "name": "2MO5",
      "amplitude": 0.024405,
      "phase_UTC": -171.635723
    }
  ],
  "secondary_offset": null
}
