{
  "id": "male-108a-mdv-uhslc-rq",
  "name": "male-108a-mdv-uhslc_rq",
  "continent": "Asia",
  "country": "Maldives",
  "latitude": 4.183,
  "longitude": 73.517,
  "type": "reference",
  "timezone": "Indian/Maldives",
  "disclaimers": "No obvious issues",
  "source": {
    "name": "TICON-4",
    "url": "https://www.seanoe.org/data/00980/109129/",
    "id": "male-108a-mdv-uhslc_rq",
    "datum": "Unspecified",
    "observation_period": {
      "start": "29/02/1988",
      "end": "31/05/1989",
      "years": 2
    }
  },
  "license": {
    "name": "cc-by-4.0",
    "url": "https://creativecommons.org/licenses/by/4.0/"
  },
  "harmonic_constituents": [
    {
      "name": "M2",
      "amplitude": 21.854603,
      "phase_UTC": -131.347395
    },
    {
      "name": "N2",
      "amplitude": 4.348562,
      "phase_UTC": -166.393062
    },
    {
      "name": "S2",
      "amplitude": 12.769123,
      "phase_UTC": -89.78282
    },
    {
      "name": "K2",
      "amplitude": 3.511556,
      "phase_UTC": -94.849232
    },
    {
      "name": "2N2",
      "amplitude": 0.340002,
      "phase_UTC": -68.66375
    },
    {
      "name": "S1",
      "amplitude": 0.908132,
      "phase_UTC": 162.413445
    },
    {
      "name": "K1",
      "amplitude": 11.093793,
      "phase_UTC": -13.442746
    },
    {
      "name": "P1",
      "amplitude": 3.674375,
      "phase_UTC": -17.557655
    },
    {
      "name": "O1",
      "amplitude": 6.083005,
      "phase_UTC": 2.23149
    },
    {
      "name": "Q1",
      "amplitude": 1.458827,
      "phase_UTC": 20.313043
    },
    {
      "name": "M1",
      "amplitude": 1.054689,
      "phase_UTC": -80.478783
    },
    {
      "name": "M4",
      "amplitude": 0.20431,
      "phase_UTC": 172.619265
    },
    {
      "name": "MM",
      "amplitude": 0.579947,
      "phase_UTC": -58.34747
    },
    {
      "name": "MF",
      "amplitude": 1.427685,
      "phase_UTC": 0.308253
    },
    {
      "name": "SA",
      "amplitude": 6.261079,
      "phase_UTC": 116.605562
    },
    {
      "name": "SSA",
      "amplitude": 4.343833,
      "phase_UTC": -105.56125
    },
    {
      "name": "T2",
      "amplitude": 1.604212,
      "phase_UTC": -126.984114
    },
    {
      "name": "J1",
      "amplitude": 0.834459,
      "phase_UTC": 6.965762
    },
    {
      "name": "L2",
      "amplitude": 0.910798,
      "phase_UTC": -26.317574
    },
    {
      "name": "R2",
      "amplitude": 0.825634,
      "phase_UTC": -25.134962
    },
    {
      "name": "2Q1",
      "amplitude": 0.27392,
      "phase_UTC": 34.62629
    },
    {
      "name": "MSF",
      "amplitude": 0.678013,
      "phase_UTC": -12.962001
    },
    {
      "name": "MSQM",
      "amplitude": 0.310846,
      "phase_UTC": 26.994265
    },
    {
      "name": "EP2",
      "amplitude": 0.283682,
      "phase_UTC": 121.25693
    },
    {
      "name": "M3",
      "amplitude": 0.289577,
      "phase_UTC": -81.941804
    },
    {
      "name": "MU2",
      "amplitude": 0.344897,
      "phase_UTC": -149.928135
    },
    {
      "name": "MTM",
      "amplitude": 0.510745,
      "phase_UTC": 77.650139
    },
    {
      "name": "NU2",
      "amplitude": 0.964357,
      "phase_UTC": -163.643257
    },
    {
      "name": "LAMBDA2",
      "amplitude": 0.665257,
      "phase_UTC": -80.15952
    },
    {
      "name": "MN4",
      "amplitude": 0.094367,
      "phase_UTC": 115.049531
    },
    {
      "name": "MS4",
      "amplitude": 0.094288,
      "phase_UTC": -129.076983
    },
    {
      "name": "MKS2",
      "amplitude": 0.518724,
      "phase_UTC": 90.072901
    },
    {
      "name": "N4",
      "amplitude": 0.05416,
      "phase_UTC": -56.092589
    },
    {
      "name": "M6",
      "amplitude": 0.079299,
      "phase_UTC": 79.438622
    },
    {
      "name": "M8",
      "amplitude": 0.027111,
      "phase_UTC": 31.995925
    },
    {
      "name": "S4",
      "amplitude": 0.064502,
      "phase_UTC": -98.682563
    },
    {
      "name": "OO1",
      "amplitude": 0.92126,
      "phase_UTC": 5.955793
    },
    {
      "name": "S3",
      "amplitude": 0.045439,
      "phase_UTC": 164.639248
    },
    {
      "name": "MA2",
      "amplitude": 0.598694,
      "phase_UTC": -116.77512
    },
    {
      "name": "MB2",
      "amplitude": 0.583537,
      "phase_UTC": 82.198599
    },
    {
      "name": "T3",
      "amplitude": 0.193151,
      "phase_UTC": -169.141899
    },
    {
      "name": "R3",
      "amplitude": 0.194195,
      "phase_UTC": 2.9278
    },
    {
      "name": "RHO1",
      "amplitude": 0.397615,
      "phase_UTC": -0.049569
    },
    {
      "name": "SGM",
      "amplitude": 0.386841,
      "phase_UTC": 178.49619
    },
    {
      "name": "3L2",
      "amplitude": 1.088586,
      "phase_UTC": -128.411699
    },
    {
      "name": "3N2",
      "amplitude": 1.666431,
      "phase_UTC": 79.682957
    },
    {
      "name": "2SM2",
      "amplitude": 0.530231,
      "phase_UTC": 160.767602
    },
    {
      "name": "2MS6",
      "amplitude": 0.224962,
      "phase_UTC": 119.155731
    },
    {
      "name": "2MK5",
      "amplitude": 0.085096,
      "phase_UTC": 99.09497
    },
    {
      "name": "2MO5",
      "amplitude": 0.068286,
      "phase_UTC": -35.643383
    }
  ],
  "secondary_offset": null
}
