{
  "id": "san-benedetto-del-tronto-san-ita-ispra",
  "name": "san_benedetto_del_tronto-san-ita-ispra",
  "continent": "Europe",
  "country": "Italy",
  "latitude": 42.955122,
  "longitude": 13.889758,
  "type": "reference",
  "timezone": "Europe/Rome",
  "disclaimers": "Possible quality control issues",
  "source": {
    "name": "TICON-4",
    "url": "https://www.seanoe.org/data/00980/109129/",
    "id": "san_benedetto_del_tronto-san-ita-ispra",
    "datum": "Unspecified",
    "observation_period": {
      "start": "18/06/2010",
      "end": "06/07/2025",
      "years": 15
    }
  },
  "license": {
    "name": "cc-by-4.0",
    "url": "https://creativecommons.org/licenses/by/4.0/"
  },
  "harmonic_constituents": [
    {
      "name": "M2",
      "amplitude": 5.646481,
      "phase_UTC": 51.458395
    },
    {
      "name": "N2",
      "amplitude": 0.876801,
      "phase_UTC": 46.663104
    },
    {
      "name": "S2",
      "amplitude": 4.062622,
      "phase_UTC": 62.681422
    },
    {
      "name": "K2",
      "amplitude": 1.219605,
      "phase_UTC": 59.844383
    },
    {
      "name": "2N2",
      "amplitude": 0.079494,
      "phase_UTC": 45.156047
    },
    {
      "name": "S1",
      "amplitude": 0.455611,
      "phase_UTC": 53.010268
    },
    {
      "name": "K1",
      "amplitude": 9.3863,
      "phase_UTC": 71.910163
    },
    {
      "name": "P1",
      "amplitude": 2.989573,
      "phase_UTC": 66.279328
    },
    {
      "name": "O1",
      "amplitude": 3.044826,
      "phase_UTC": 60.384505
    },
    {
      "name": "Q1",
      "amplitude": 0.528405,
      "phase_UTC": 77.71459
    },
    {
      "name": "M1",
      "amplitude": 0.236618,
      "phase_UTC": -13.339121
    },
    {
      "name": "M4",
      "amplitude": 0.091183,
      "phase_UTC": -25.471901
    },
    {
      "name": "MM",
      "amplitude": 0.636237,
      "phase_UTC": -65.756122
    },
    {
      "name": "MF",
      "amplitude": 0.263585,
      "phase_UTC": 149.7279
    },
    {
      "name": "SA",
      "amplitude": 5.527489,
      "phase_UTC": -146.030212
    },
    {
      "name": "SSA",
      "amplitude": 3.323693,
      "phase_UTC": 124.162801
    },
    {
      "name": "T2",
      "amplitude": 0.220006,
      "phase_UTC": 86.545237
    },
    {
      "name": "J1",
      "amplitude": 0.572122,
      "phase_UTC": 99.005267
    },
    {
      "name": "L2",
      "amplitude": 0.21834,
      "phase_UTC": 46.464871
    },
    {
      "name": "R2",
      "amplitude": 0.104736,
      "phase_UTC": 87.949474
    },
    {
      "name": "2Q1",
      "amplitude": 0.106408,
      "phase_UTC": 51.576902
    },
    {
      "name": "MSF",
      "amplitude": 0.468591,
      "phase_UTC": -94.325856
    },
    {
      "name": "MSQM",
      "amplitude": 0.082064,
      "phase_UTC": 132.788001
    },
    {
      "name": "EP2",
      "amplitude": 0.012186,
      "phase_UTC": 66.002778
    },
    {
      "name": "M3",
      "amplitude": 0.336217,
      "phase_UTC": -12.119383
    },
    {
      "name": "MU2",
      "amplitude": 0.095426,
      "phase_UTC": 67.325728
    },
    {
      "name": "MTM",
      "amplitude": 0.233986,
      "phase_UTC": 27.558778
    },
    {
      "name": "NU2",
      "amplitude": 0.161127,
      "phase_UTC": 46.520821
    },
    {
      "name": "LAMBDA2",
      "amplitude": 0.077263,
      "phase_UTC": 70.74901
    },
    {
      "name": "MN4",
      "amplitude": 0.037702,
      "phase_UTC": -52.948118
    },
    {
      "name": "MS4",
      "amplitude": 0.053418,
      "phase_UTC": 32.391602
    },
    {
      "name": "MKS2",
      "amplitude": 0.010673,
      "phase_UTC": 106.54015
    },
    {
      "name": "N4",
      "amplitude": 0.00984,
      "phase_UTC": -142.915057
    },
    {
      "name": "M6",
      "amplitude": 0.007164,
      "phase_UTC": 156.685852
    },
    {
      "name": "M8",
      "amplitude": 0.002487,
      "phase_UTC": 3.215963
    },
    {
      "name": "S4",
      "amplitude": 0.071632,
      "phase_UTC": 53.458429
    },
    {
      "name": "OO1",
      "amplitude": 0.542626,
      "phase_UTC": 119.764388
    },
    {
      "name": "S3",
      "amplitude": 0.003363,
      "phase_UTC": 119.726982
    },
    {
      "name": "MA2",
      "amplitude": 0.039578,
      "phase_UTC": -88.708401
    },
    {
      "name": "MB2",
      "amplitude": 0.134141,
      "phase_UTC": -164.69444
    },
    {
      "name": "T3",
      "amplitude": 0.170928,
      "phase_UTC": 10.628522
    },
    {
      "name": "R3",
      "amplitude": 0.166977,
      "phase_UTC": -157.890879
    },
    {
      "name": "RHO1",
      "amplitude": 0.110971,
      "phase_UTC": 71.259436
    },
    {
      "name": "SGM",
      "amplitude": 0.134576,
      "phase_UTC": -118.183143
    },
    {
      "name": "3L2",
      "amplitude": 0.062613,
      "phase_UTC": 16.692822
    },
    {
      "name": "3N2",
      "amplitude": 0.0565,
      "phase_UTC": 40.564397
    },
    {
      "name": "2SM2",
      "amplitude": 0.076173,
      "phase_UTC": -133.134618
    },
    {
      "name": "2MS6",
      "amplitude": 0.030986,
      "phase_UTC": -151.572016
    },
    {
      "name": "2MK5",
      "amplitude": 0.01276,
      "phase_UTC": -37.664607
    },
    {
      "name": "2MO5",
      "amplitude": 0.006502,
      "phase_UTC": 105.974673
    }
  ],
  "secondary_offset": null
}
