{
  "id": "barataria-waterway-s-of-lafitte-la-292859090004000-usa-usgs",
  "name": "barataria_waterway_s_of_lafitte_la-292859090004000-usa-usgs",
  "continent": "Americas",
  "country": "United States",
  "latitude": 29.483056,
  "longitude": -90.011111,
  "type": "reference",
  "timezone": "America/Chicago",
  "disclaimers": "Possible quality control issues",
  "source": {
    "name": "TICON-4",
    "url": "https://www.seanoe.org/data/00980/109129/",
    "id": "barataria_waterway_s_of_lafitte_la-292859090004000-usa-usgs",
    "datum": "USGS Station Datum (see station page for tie to geocentric datum)",
    "observation_period": {
      "start": "01/10/2007",
      "end": "21/02/2017",
      "years": 9
    }
  },
  "license": {
    "name": "cc-by-4.0",
    "url": "https://creativecommons.org/licenses/by/4.0/"
  },
  "harmonic_constituents": [
    {
      "name": "M2",
      "amplitude": 0.773841,
      "phase_UTC": -117.369725
    },
    {
      "name": "N2",
      "amplitude": 0.276223,
      "phase_UTC": -119.015978
    },
    {
      "name": "S2",
      "amplitude": 0.414328,
      "phase_UTC": -143.186533
    },
    {
      "name": "K2",
      "amplitude": 0.286402,
      "phase_UTC": -146.294144
    },
    {
      "name": "2N2",
      "amplitude": 0.023883,
      "phase_UTC": -73.299087
    },
    {
      "name": "S1",
      "amplitude": 0.40344,
      "phase_UTC": -50.622688
    },
    {
      "name": "K1",
      "amplitude": 8.494744,
      "phase_UTC": 69.000248
    },
    {
      "name": "P1",
      "amplitude": 2.298575,
      "phase_UTC": 62.541389
    },
    {
      "name": "O1",
      "amplitude": 8.316805,
      "phase_UTC": 61.367578
    },
    {
      "name": "Q1",
      "amplitude": 1.658452,
      "phase_UTC": 50.88726
    },
    {
      "name": "M1",
      "amplitude": 0.258704,
      "phase_UTC": 30.013536
    },
    {
      "name": "M4",
      "amplitude": 0.186443,
      "phase_UTC": 126.580264
    },
    {
      "name": "MM",
      "amplitude": 0.608488,
      "phase_UTC": 78.486768
    },
    {
      "name": "MF",
      "amplitude": 1.754065,
      "phase_UTC": -89.267542
    },
    {
      "name": "SA",
      "amplitude": 11.080796,
      "phase_UTC": 142.137883
    },
    {
      "name": "SSA",
      "amplitude": 6.632574,
      "phase_UTC": 65.127703
    },
    {
      "name": "T2",
      "amplitude": 0.04745,
      "phase_UTC": 29.772003
    },
    {
      "name": "J1",
      "amplitude": 0.342847,
      "phase_UTC": 84.852068
    },
    {
      "name": "L2",
      "amplitude": 0.078123,
      "phase_UTC": -99.088233
    },
    {
      "name": "R2",
      "amplitude": 0.045318,
      "phase_UTC": -49.289947
    },
    {
      "name": "2Q1",
      "amplitude": 0.266658,
      "phase_UTC": 60.88929
    },
    {
      "name": "MSF",
      "amplitude": 0.445272,
      "phase_UTC": -44.049202
    },
    {
      "name": "MSQM",
      "amplitude": 0.401433,
      "phase_UTC": -113.822571
    },
    {
      "name": "EP2",
      "amplitude": 0.076311,
      "phase_UTC": 36.783088
    },
    {
      "name": "M3",
      "amplitude": 0.054744,
      "phase_UTC": 172.160272
    },
    {
      "name": "MU2",
      "amplitude": 0.033486,
      "phase_UTC": 115.817108
    },
    {
      "name": "MTM",
      "amplitude": 0.766277,
      "phase_UTC": 56.092403
    },
    {
      "name": "NU2",
      "amplitude": 0.083405,
      "phase_UTC": -115.754414
    },
    {
      "name": "LAMBDA2",
      "amplitude": 0.034689,
      "phase_UTC": -131.189845
    },
    {
      "name": "MN4",
      "amplitude": 0.095056,
      "phase_UTC": 90.389148
    },
    {
      "name": "MS4",
      "amplitude": 0.10941,
      "phase_UTC": 102.874531
    },
    {
      "name": "MKS2",
      "amplitude": 0.031298,
      "phase_UTC": -59.075974
    },
    {
      "name": "N4",
      "amplitude": 0.029921,
      "phase_UTC": -4.498743
    },
    {
      "name": "M6",
      "amplitude": 0.036271,
      "phase_UTC": -135.923612
    },
    {
      "name": "M8",
      "amplitude": 0.025439,
      "phase_UTC": -166.510361
    },
    {
      "name": "S4",
      "amplitude": 0.030313,
      "phase_UTC": -97.439821
    },
    {
      "name": "OO1",
      "amplitude": 0.782827,
      "phase_UTC": 41.056896
    },
    {
      "name": "S3",
      "amplitude": 0.052455,
      "phase_UTC": 169.783534
    },
    {
      "name": "MA2",
      "amplitude": 0.123373,
      "phase_UTC": 58.859629
    },
    {
      "name": "MB2",
      "amplitude": 0.027938,
      "phase_UTC": 93.626661
    },
    {
      "name": "T3",
      "amplitude": 0.005103,
      "phase_UTC": -132.963753
    },
    {
      "name": "R3",
      "amplitude": 0.05855,
      "phase_UTC": -144.527074
    },
    {
      "name": "RHO1",
      "amplitude": 0.229045,
      "phase_UTC": 40.63895
    },
    {
      "name": "SGM",
      "amplitude": 0.186372,
      "phase_UTC": -126.886893
    },
    {
      "name": "3L2",
      "amplitude": 0.02871,
      "phase_UTC": -109.835139
    },
    {
      "name": "3N2",
      "amplitude": 0.084058,
      "phase_UTC": 12.761208
    },
    {
      "name": "2SM2",
      "amplitude": 0.038544,
      "phase_UTC": 10.690816
    },
    {
      "name": "2MS6",
      "amplitude": 0.027495,
      "phase_UTC": 25.783
    },
    {
      "name": "2MK5",
      "amplitude": 0.04551,
      "phase_UTC": 21.515955
    },
    {
      "name": "2MO5",
      "amplitude": 0.02532,
      "phase_UTC": -172.667466
    }
  ],
  "secondary_offset": null
}
