{
  "id": "guantanamo-bay-9731158-usa-noaa",
  "name": "guantanamo_bay-9731158-usa-noaa",
  "continent": "Americas",
  "country": "United States",
  "latitude": 19.9067,
  "longitude": -75.1467,
  "type": "reference",
  "timezone": "America/New_York",
  "disclaimers": "No obvious issues",
  "source": {
    "name": "TICON-4",
    "url": "https://www.seanoe.org/data/00980/109129/",
    "id": "guantanamo_bay-9731158-usa-noaa",
    "datum": "Station Datum",
    "observation_period": {
      "start": "21/06/1995",
      "end": "31/01/1997",
      "years": 3
    }
  },
  "license": {
    "name": "cc-by-4.0",
    "url": "https://creativecommons.org/licenses/by/4.0/"
  },
  "harmonic_constituents": [
    {
      "name": "M2",
      "amplitude": 13.901262,
      "phase_UTC": 38.828413
    },
    {
      "name": "N2",
      "amplitude": 2.888673,
      "phase_UTC": 35.925462
    },
    {
      "name": "S2",
      "amplitude": 4.027268,
      "phase_UTC": 42.146234
    },
    {
      "name": "K2",
      "amplitude": 1.138202,
      "phase_UTC": 35.274784
    },
    {
      "name": "2N2",
      "amplitude": 0.325815,
      "phase_UTC": 29.502282
    },
    {
      "name": "S1",
      "amplitude": 0.325608,
      "phase_UTC": 149.212492
    },
    {
      "name": "K1",
      "amplitude": 6.787135,
      "phase_UTC": -141.082921
    },
    {
      "name": "P1",
      "amplitude": 1.962163,
      "phase_UTC": -138.480926
    },
    {
      "name": "O1",
      "amplitude": 3.269027,
      "phase_UTC": -145.861209
    },
    {
      "name": "Q1",
      "amplitude": 0.322569,
      "phase_UTC": -145.363979
    },
    {
      "name": "M1",
      "amplitude": 0.194078,
      "phase_UTC": 145.392363
    },
    {
      "name": "M4",
      "amplitude": 0.128711,
      "phase_UTC": 94.351091
    },
    {
      "name": "MM",
      "amplitude": 1.228509,
      "phase_UTC": -13.433138
    },
    {
      "name": "MF",
      "amplitude": 2.040089,
      "phase_UTC": -2.402855
    },
    {
      "name": "SA",
      "amplitude": 8.4899,
      "phase_UTC": -164.813927
    },
    {
      "name": "SSA",
      "amplitude": 2.528895,
      "phase_UTC": -58.194325
    },
    {
      "name": "T2",
      "amplitude": 0.421416,
      "phase_UTC": 33.811802
    },
    {
      "name": "J1",
      "amplitude": 0.407166,
      "phase_UTC": -132.563871
    },
    {
      "name": "L2",
      "amplitude": 0.853972,
      "phase_UTC": 72.924561
    },
    {
      "name": "R2",
      "amplitude": 0.106271,
      "phase_UTC": 117.848629
    },
    {
      "name": "2Q1",
      "amplitude": 0.009384,
      "phase_UTC": -127.567236
    },
    {
      "name": "MSF",
      "amplitude": 0.548968,
      "phase_UTC": 0.121231
    },
    {
      "name": "MSQM",
      "amplitude": 0.25359,
      "phase_UTC": -126.375251
    },
    {
      "name": "EP2",
      "amplitude": 0.070188,
      "phase_UTC": -106.505194
    },
    {
      "name": "M3",
      "amplitude": 0.118932,
      "phase_UTC": 124.156599
    },
    {
      "name": "MU2",
      "amplitude": 0.476673,
      "phase_UTC": -25.923101
    },
    {
      "name": "MTM",
      "amplitude": 0.228143,
      "phase_UTC": -2.239851
    },
    {
      "name": "NU2",
      "amplitude": 0.567863,
      "phase_UTC": 25.142297
    },
    {
      "name": "LAMBDA2",
      "amplitude": 0.106408,
      "phase_UTC": 18.97046
    },
    {
      "name": "MN4",
      "amplitude": 0.079574,
      "phase_UTC": 81.779394
    },
    {
      "name": "MS4",
      "amplitude": 0.088341,
      "phase_UTC": 74.474646
    },
    {
      "name": "MKS2",
      "amplitude": 0.500713,
      "phase_UTC": -59.219853
    },
    {
      "name": "N4",
      "amplitude": 0.031496,
      "phase_UTC": 42.603024
    },
    {
      "name": "M6",
      "amplitude": 0.111813,
      "phase_UTC": 70.987038
    },
    {
      "name": "M8",
      "amplitude": 0.023962,
      "phase_UTC": -113.977677
    },
    {
      "name": "S4",
      "amplitude": 0.054886,
      "phase_UTC": -9.75806
    },
    {
      "name": "OO1",
      "amplitude": 0.153724,
      "phase_UTC": -160.438285
    },
    {
      "name": "S3",
      "amplitude": 0.057994,
      "phase_UTC": -112.267543
    },
    {
      "name": "MA2",
      "amplitude": 0.377781,
      "phase_UTC": 38.507214
    },
    {
      "name": "MB2",
      "amplitude": 0.793951,
      "phase_UTC": 134.854751
    },
    {
      "name": "T3",
      "amplitude": 0.03527,
      "phase_UTC": 8.096062
    },
    {
      "name": "R3",
      "amplitude": 0.033297,
      "phase_UTC": 7.378654
    },
    {
      "name": "RHO1",
      "amplitude": 0.055613,
      "phase_UTC": -155.101033
    },
    {
      "name": "SGM",
      "amplitude": 0.036039,
      "phase_UTC": -99.714908
    },
    {
      "name": "3L2",
      "amplitude": 0.93063,
      "phase_UTC": -72.940266
    },
    {
      "name": "3N2",
      "amplitude": 0.952461,
      "phase_UTC": 128.678039
    },
    {
      "name": "2SM2",
      "amplitude": 0.09427,
      "phase_UTC": 105.007325
    },
    {
      "name": "2MS6",
      "amplitude": 0.076186,
      "phase_UTC": -150.902459
    },
    {
      "name": "2MK5",
      "amplitude": 0.02893,
      "phase_UTC": -14.663064
    },
    {
      "name": "2MO5",
      "amplitude": 0.024145,
      "phase_UTC": 124.880593
    }
  ],
  "secondary_offset": null
}
