{
  "id": "prince-rupert-540-can-uhslc-fd",
  "name": "prince_rupert-540-can-uhslc_fd",
  "continent": "Americas",
  "country": "Canada",
  "latitude": 54.317,
  "longitude": -130.333,
  "type": "reference",
  "timezone": "America/Vancouver",
  "disclaimers": "No obvious issues",
  "source": {
    "name": "TICON-4",
    "url": "https://www.seanoe.org/data/00980/109129/",
    "id": "prince_rupert-540-can-uhslc_fd",
    "datum": "Unspecified",
    "observation_period": {
      "start": "01/01/1909",
      "end": "30/06/2025",
      "years": 100
    }
  },
  "license": {
    "name": "cc-by-4.0",
    "url": "https://creativecommons.org/licenses/by/4.0/"
  },
  "harmonic_constituents": [
    {
      "name": "M2",
      "amplitude": 195.149964,
      "phase_UTC": -92.618172
    },
    {
      "name": "N2",
      "amplitude": 39.161163,
      "phase_UTC": -116.957582
    },
    {
      "name": "S2",
      "amplitude": 64.151846,
      "phase_UTC": -60.905802
    },
    {
      "name": "K2",
      "amplitude": 17.512863,
      "phase_UTC": -68.389054
    },
    {
      "name": "2N2",
      "amplitude": 4.422227,
      "phase_UTC": -141.996888
    },
    {
      "name": "S1",
      "amplitude": 1.237469,
      "phase_UTC": 41.345259
    },
    {
      "name": "K1",
      "amplitude": 51.102108,
      "phase_UTC": -100.222467
    },
    {
      "name": "P1",
      "amplitude": 16.061602,
      "phase_UTC": -103.569983
    },
    {
      "name": "O1",
      "amplitude": 30.981086,
      "phase_UTC": -116.081234
    },
    {
      "name": "Q1",
      "amplitude": 5.483482,
      "phase_UTC": -124.085379
    },
    {
      "name": "M1",
      "amplitude": 2.109271,
      "phase_UTC": 159.936472
    },
    {
      "name": "M4",
      "amplitude": 0.645811,
      "phase_UTC": -12.989637
    },
    {
      "name": "MM",
      "amplitude": 1.176495,
      "phase_UTC": -177.448455
    },
    {
      "name": "MF",
      "amplitude": 2.2403,
      "phase_UTC": 177.141943
    },
    {
      "name": "SA",
      "amplitude": 10.848548,
      "phase_UTC": -87.421565
    },
    {
      "name": "SSA",
      "amplitude": 2.787541,
      "phase_UTC": 149.97268
    },
    {
      "name": "T2",
      "amplitude": 3.683961,
      "phase_UTC": -70.591368
    },
    {
      "name": "J1",
      "amplitude": 2.778659,
      "phase_UTC": -86.900473
    },
    {
      "name": "L2",
      "amplitude": 4.632172,
      "phase_UTC": -79.318125
    },
    {
      "name": "R2",
      "amplitude": 0.407966,
      "phase_UTC": 12.490014
    },
    {
      "name": "2Q1",
      "amplitude": 0.652562,
      "phase_UTC": -121.653254
    },
    {
      "name": "MSF",
      "amplitude": 0.155064,
      "phase_UTC": 46.390365
    },
    {
      "name": "MSQM",
      "amplitude": 0.058271,
      "phase_UTC": -74.435087
    },
    {
      "name": "EP2",
      "amplitude": 0.866348,
      "phase_UTC": -123.281639
    },
    {
      "name": "M3",
      "amplitude": 2.056074,
      "phase_UTC": -24.0044
    },
    {
      "name": "MU2",
      "amplitude": 4.070564,
      "phase_UTC": -126.192144
    },
    {
      "name": "MTM",
      "amplitude": 0.408787,
      "phase_UTC": 160.298861
    },
    {
      "name": "NU2",
      "amplitude": 7.686667,
      "phase_UTC": -113.79388
    },
    {
      "name": "LAMBDA2",
      "amplitude": 1.198111,
      "phase_UTC": -91.104407
    },
    {
      "name": "MN4",
      "amplitude": 0.326261,
      "phase_UTC": -49.190763
    },
    {
      "name": "MS4",
      "amplitude": 0.282134,
      "phase_UTC": 6.640545
    },
    {
      "name": "MKS2",
      "amplitude": 0.038846,
      "phase_UTC": -162.180536
    },
    {
      "name": "N4",
      "amplitude": 0.052841,
      "phase_UTC": -63.159724
    },
    {
      "name": "M6",
      "amplitude": 0.381788,
      "phase_UTC": 152.150908
    },
    {
      "name": "M8",
      "amplitude": 0.230541,
      "phase_UTC": 66.742064
    },
    {
      "name": "S4",
      "amplitude": 0.192128,
      "phase_UTC": 19.447758
    },
    {
      "name": "OO1",
      "amplitude": 1.823289,
      "phase_UTC": -68.037071
    },
    {
      "name": "S3",
      "amplitude": 1.305323,
      "phase_UTC": -177.936473
    },
    {
      "name": "MA2",
      "amplitude": 1.037603,
      "phase_UTC": -177.15477
    },
    {
      "name": "MB2",
      "amplitude": 1.25782,
      "phase_UTC": 148.040475
    },
    {
      "name": "T3",
      "amplitude": 1.520424,
      "phase_UTC": -134.760694
    },
    {
      "name": "R3",
      "amplitude": 1.817979,
      "phase_UTC": 44.890589
    },
    {
      "name": "RHO1",
      "amplitude": 1.049682,
      "phase_UTC": -123.866737
    },
    {
      "name": "SGM",
      "amplitude": 0.756606,
      "phase_UTC": 62.034914
    },
    {
      "name": "3L2",
      "amplitude": 0.581348,
      "phase_UTC": 80.865494
    },
    {
      "name": "3N2",
      "amplitude": 0.626547,
      "phase_UTC": 142.115411
    },
    {
      "name": "2SM2",
      "amplitude": 0.44587,
      "phase_UTC": 87.372193
    },
    {
      "name": "2MS6",
      "amplitude": 0.317582,
      "phase_UTC": -172.150716
    },
    {
      "name": "2MK5",
      "amplitude": 0.426752,
      "phase_UTC": 4.140883
    },
    {
      "name": "2MO5",
      "amplitude": 0.199812,
      "phase_UTC": 149.115507
    }
  ],
  "secondary_offset": null
}
