{
  "id": "yavaros-677-mex-unam-hist",
  "name": "yavaros-677-mex-unam_hist",
  "continent": "Americas",
  "country": "Mexico",
  "latitude": 26.705,
  "longitude": -109.508333,
  "type": "reference",
  "timezone": "America/Hermosillo",
  "disclaimers": "No obvious issues",
  "source": {
    "name": "TICON-4",
    "url": "https://www.seanoe.org/data/00980/109129/",
    "id": "yavaros-677-mex-unam_hist",
    "datum": "Unspecified",
    "observation_period": {
      "start": "01/01/1970",
      "end": "31/12/1973",
      "years": 4
    }
  },
  "license": {
    "name": "cc-by-4.0",
    "url": "https://creativecommons.org/licenses/by/4.0/"
  },
  "harmonic_constituents": [
    {
      "name": "M2",
      "amplitude": 20.657516,
      "phase_UTC": 135.909039
    },
    {
      "name": "N2",
      "amplitude": 4.69943,
      "phase_UTC": 142.689806
    },
    {
      "name": "S2",
      "amplitude": 15.583955,
      "phase_UTC": 132.373628
    },
    {
      "name": "K2",
      "amplitude": 5.046454,
      "phase_UTC": 126.095538
    },
    {
      "name": "2N2",
      "amplitude": 0.561562,
      "phase_UTC": 148.216351
    },
    {
      "name": "S1",
      "amplitude": 1.181515,
      "phase_UTC": -72.049571
    },
    {
      "name": "K1",
      "amplitude": 25.373757,
      "phase_UTC": -175.755433
    },
    {
      "name": "P1",
      "amplitude": 8.135999,
      "phase_UTC": -175.02074
    },
    {
      "name": "O1",
      "amplitude": 17.210349,
      "phase_UTC": 173.058909
    },
    {
      "name": "Q1",
      "amplitude": 2.998414,
      "phase_UTC": 168.495225
    },
    {
      "name": "M1",
      "amplitude": 1.613723,
      "phase_UTC": 135.926041
    },
    {
      "name": "M4",
      "amplitude": 1.004219,
      "phase_UTC": 59.092145
    },
    {
      "name": "MM",
      "amplitude": 1.035603,
      "phase_UTC": 47.293867
    },
    {
      "name": "MF",
      "amplitude": 0.295678,
      "phase_UTC": 75.252794
    },
    {
      "name": "SA",
      "amplitude": 17.848583,
      "phase_UTC": 139.14011
    },
    {
      "name": "SSA",
      "amplitude": 3.721234,
      "phase_UTC": -93.535715
    },
    {
      "name": "T2",
      "amplitude": 1.646625,
      "phase_UTC": 133.691442
    },
    {
      "name": "J1",
      "amplitude": 1.318933,
      "phase_UTC": -165.959463
    },
    {
      "name": "L2",
      "amplitude": 0.867622,
      "phase_UTC": 104.113141
    },
    {
      "name": "R2",
      "amplitude": 2.301435,
      "phase_UTC": 129.886466
    },
    {
      "name": "2Q1",
      "amplitude": 0.517199,
      "phase_UTC": 159.112655
    },
    {
      "name": "MSF",
      "amplitude": 0.411678,
      "phase_UTC": -23.242729
    },
    {
      "name": "MSQM",
      "amplitude": 0.164794,
      "phase_UTC": -105.671492
    },
    {
      "name": "EP2",
      "amplitude": 0.283268,
      "phase_UTC": 170.030978
    },
    {
      "name": "M3",
      "amplitude": 0.573809,
      "phase_UTC": -113.043508
    },
    {
      "name": "MU2",
      "amplitude": 1.265829,
      "phase_UTC": 177.318775
    },
    {
      "name": "MTM",
      "amplitude": 0.25819,
      "phase_UTC": 153.834558
    },
    {
      "name": "NU2",
      "amplitude": 1.449543,
      "phase_UTC": 133.996125
    },
    {
      "name": "LAMBDA2",
      "amplitude": 1.028679,
      "phase_UTC": 117.848328
    },
    {
      "name": "MN4",
      "amplitude": 0.23632,
      "phase_UTC": 23.712746
    },
    {
      "name": "MS4",
      "amplitude": 0.684034,
      "phase_UTC": 111.166701
    },
    {
      "name": "MKS2",
      "amplitude": 0.065791,
      "phase_UTC": -50.983944
    },
    {
      "name": "N4",
      "amplitude": 0.042341,
      "phase_UTC": -60.814983
    },
    {
      "name": "M6",
      "amplitude": 0.09806,
      "phase_UTC": 84.107116
    },
    {
      "name": "M8",
      "amplitude": 0.02667,
      "phase_UTC": 11.560004
    },
    {
      "name": "S4",
      "amplitude": 0.141467,
      "phase_UTC": -35.767304
    },
    {
      "name": "OO1",
      "amplitude": 1.027491,
      "phase_UTC": -173.783504
    },
    {
      "name": "S3",
      "amplitude": 0.224203,
      "phase_UTC": -152.799243
    },
    {
      "name": "MA2",
      "amplitude": 1.249558,
      "phase_UTC": -132.26268
    },
    {
      "name": "MB2",
      "amplitude": 1.387879,
      "phase_UTC": -119.809589
    },
    {
      "name": "T3",
      "amplitude": 0.127175,
      "phase_UTC": -109.036572
    },
    {
      "name": "R3",
      "amplitude": 0.54673,
      "phase_UTC": 141.85734
    },
    {
      "name": "RHO1",
      "amplitude": 0.981657,
      "phase_UTC": 178.122372
    },
    {
      "name": "SGM",
      "amplitude": 0.48851,
      "phase_UTC": 54.761184
    },
    {
      "name": "3L2",
      "amplitude": 0.539975,
      "phase_UTC": 36.565601
    },
    {
      "name": "3N2",
      "amplitude": 0.273627,
      "phase_UTC": 15.364285
    },
    {
      "name": "2SM2",
      "amplitude": 0.48667,
      "phase_UTC": -94.331882
    },
    {
      "name": "2MS6",
      "amplitude": 0.199406,
      "phase_UTC": 89.261022
    },
    {
      "name": "2MK5",
      "amplitude": 0.202421,
      "phase_UTC": 27.221617
    },
    {
      "name": "2MO5",
      "amplitude": 0.145572,
      "phase_UTC": -156.391707
    }
  ],
  "secondary_offset": null
}
