{
  "id": "nanaoko-0106-jpn-jodc-pahb",
  "name": "nanaoko-0106-jpn-jodc_pahb",
  "continent": "Asia",
  "country": "Japan",
  "latitude": 37.04945,
  "longitude": 136.968333,
  "type": "reference",
  "timezone": "Asia/Tokyo",
  "disclaimers": "No obvious issues",
  "source": {
    "name": "TICON-4",
    "url": "https://www.seanoe.org/data/00980/109129/",
    "id": "nanaoko-0106-jpn-jodc_pahb",
    "datum": "Zero of Tide Height",
    "observation_period": {
      "start": "31/12/2000",
      "end": "31/12/2023",
      "years": 24
    }
  },
  "license": {
    "name": "cc-by-4.0",
    "url": "https://creativecommons.org/licenses/by/4.0/"
  },
  "harmonic_constituents": [
    {
      "name": "M2",
      "amplitude": 6.150548,
      "phase_UTC": 170.05127
    },
    {
      "name": "N2",
      "amplitude": 1.550527,
      "phase_UTC": 157.083057
    },
    {
      "name": "S2",
      "amplitude": 2.224012,
      "phase_UTC": -163.907815
    },
    {
      "name": "K2",
      "amplitude": 0.693831,
      "phase_UTC": -171.990072
    },
    {
      "name": "2N2",
      "amplitude": 0.23083,
      "phase_UTC": 127.853922
    },
    {
      "name": "S1",
      "amplitude": 0.108134,
      "phase_UTC": -94.253867
    },
    {
      "name": "K1",
      "amplitude": 5.331503,
      "phase_UTC": -149.374548
    },
    {
      "name": "P1",
      "amplitude": 1.72515,
      "phase_UTC": -151.965302
    },
    {
      "name": "O1",
      "amplitude": 5.389881,
      "phase_UTC": -174.973451
    },
    {
      "name": "Q1",
      "amplitude": 1.212116,
      "phase_UTC": 168.935629
    },
    {
      "name": "M1",
      "amplitude": 0.243283,
      "phase_UTC": 98.68915
    },
    {
      "name": "M4",
      "amplitude": 0.163969,
      "phase_UTC": -86.565125
    },
    {
      "name": "MM",
      "amplitude": 0.347308,
      "phase_UTC": 61.050803
    },
    {
      "name": "MF",
      "amplitude": 1.167991,
      "phase_UTC": -173.055581
    },
    {
      "name": "SA",
      "amplitude": 16.552368,
      "phase_UTC": 161.81596
    },
    {
      "name": "SSA",
      "amplitude": 2.425526,
      "phase_UTC": -126.330345
    },
    {
      "name": "T2",
      "amplitude": 0.193977,
      "phase_UTC": -159.285214
    },
    {
      "name": "J1",
      "amplitude": 0.215773,
      "phase_UTC": -125.980282
    },
    {
      "name": "L2",
      "amplitude": 0.099221,
      "phase_UTC": 143.337721
    },
    {
      "name": "R2",
      "amplitude": 0.127429,
      "phase_UTC": 130.094994
    },
    {
      "name": "2Q1",
      "amplitude": 0.173472,
      "phase_UTC": 151.643062
    },
    {
      "name": "MSF",
      "amplitude": 0.174323,
      "phase_UTC": 38.452678
    },
    {
      "name": "MSQM",
      "amplitude": 0.249052,
      "phase_UTC": -37.174758
    },
    {
      "name": "EP2",
      "amplitude": 0.070752,
      "phase_UTC": 94.7043
    },
    {
      "name": "M3",
      "amplitude": 0.042438,
      "phase_UTC": 123.175
    },
    {
      "name": "MU2",
      "amplitude": 0.466079,
      "phase_UTC": 124.132306
    },
    {
      "name": "MTM",
      "amplitude": 0.482676,
      "phase_UTC": -148.525144
    },
    {
      "name": "NU2",
      "amplitude": 0.238913,
      "phase_UTC": 160.47738
    },
    {
      "name": "LAMBDA2",
      "amplitude": 0.034585,
      "phase_UTC": 109.256963
    },
    {
      "name": "MN4",
      "amplitude": 0.077618,
      "phase_UTC": -111.261518
    },
    {
      "name": "MS4",
      "amplitude": 0.060158,
      "phase_UTC": -52.851611
    },
    {
      "name": "MKS2",
      "amplitude": 0.031696,
      "phase_UTC": -96.653823
    },
    {
      "name": "N4",
      "amplitude": 0.022992,
      "phase_UTC": -126.078769
    },
    {
      "name": "M6",
      "amplitude": 0.043328,
      "phase_UTC": -51.793033
    },
    {
      "name": "M8",
      "amplitude": 0.007413,
      "phase_UTC": 122.463118
    },
    {
      "name": "S4",
      "amplitude": 0.009539,
      "phase_UTC": 119.329207
    },
    {
      "name": "OO1",
      "amplitude": 0.192921,
      "phase_UTC": -101.673838
    },
    {
      "name": "S3",
      "amplitude": 0.015367,
      "phase_UTC": 164.109855
    },
    {
      "name": "MA2",
      "amplitude": 0.182756,
      "phase_UTC": -149.84648
    },
    {
      "name": "MB2",
      "amplitude": 0.194257,
      "phase_UTC": 148.924664
    },
    {
      "name": "T3",
      "amplitude": 0.008619,
      "phase_UTC": 12.943849
    },
    {
      "name": "R3",
      "amplitude": 0.054662,
      "phase_UTC": -145.508076
    },
    {
      "name": "RHO1",
      "amplitude": 0.210096,
      "phase_UTC": 169.251774
    },
    {
      "name": "SGM",
      "amplitude": 0.126315,
      "phase_UTC": -65.50284
    },
    {
      "name": "3L2",
      "amplitude": 0.031616,
      "phase_UTC": 32.440806
    },
    {
      "name": "3N2",
      "amplitude": 0.038052,
      "phase_UTC": 17.691251
    },
    {
      "name": "2SM2",
      "amplitude": 0.043409,
      "phase_UTC": -58.034732
    },
    {
      "name": "2MS6",
      "amplitude": 0.076944,
      "phase_UTC": -4.351684
    },
    {
      "name": "2MK5",
      "amplitude": 0.001775,
      "phase_UTC": -57.066244
    },
    {
      "name": "2MO5",
      "amplitude": 0.008506,
      "phase_UTC": -134.451046
    }
  ],
  "secondary_offset": null
}
