{
  "id": "aunuu-407-asm-uhslc-fd",
  "name": "aunuu-407-asm-uhslc_fd",
  "continent": "Oceania",
  "country": "American Samoa",
  "latitude": -14.283,
  "longitude": -170.562,
  "type": "reference",
  "timezone": "Pacific/Pago_Pago",
  "disclaimers": "No obvious issues",
  "source": {
    "name": "TICON-4",
    "url": "https://www.seanoe.org/data/00980/109129/",
    "id": "aunuu-407-asm-uhslc_fd",
    "datum": "Unspecified",
    "observation_period": {
      "start": "27/04/2023",
      "end": "30/06/2025",
      "years": 3
    }
  },
  "license": {
    "name": "cc-by-4.0",
    "url": "https://creativecommons.org/licenses/by/4.0/"
  },
  "harmonic_constituents": [
    {
      "name": "M2",
      "amplitude": 36.950926,
      "phase_UTC": 177.830704
    },
    {
      "name": "N2",
      "amplitude": 10.742947,
      "phase_UTC": 158.519277
    },
    {
      "name": "S2",
      "amplitude": 6.446143,
      "phase_UTC": 160.708005
    },
    {
      "name": "K2",
      "amplitude": 1.774976,
      "phase_UTC": 145.445478
    },
    {
      "name": "2N2",
      "amplitude": 1.825789,
      "phase_UTC": 144.573087
    },
    {
      "name": "S1",
      "amplitude": 0.280707,
      "phase_UTC": -147.667174
    },
    {
      "name": "K1",
      "amplitude": 4.209363,
      "phase_UTC": 82.12104
    },
    {
      "name": "P1",
      "amplitude": 0.974771,
      "phase_UTC": 68.896322
    },
    {
      "name": "O1",
      "amplitude": 2.845354,
      "phase_UTC": 68.264896
    },
    {
      "name": "Q1",
      "amplitude": 0.372384,
      "phase_UTC": 53.122755
    },
    {
      "name": "M1",
      "amplitude": 0.241054,
      "phase_UTC": -73.688635
    },
    {
      "name": "M4",
      "amplitude": 0.797193,
      "phase_UTC": 43.123748
    },
    {
      "name": "MM",
      "amplitude": 0.866486,
      "phase_UTC": 38.004988
    },
    {
      "name": "MF",
      "amplitude": 0.975575,
      "phase_UTC": 26.275925
    },
    {
      "name": "SA",
      "amplitude": 3.885321,
      "phase_UTC": 33.209986
    },
    {
      "name": "SSA",
      "amplitude": 1.913743,
      "phase_UTC": -1.00103
    },
    {
      "name": "T2",
      "amplitude": 0.25833,
      "phase_UTC": 135.881176
    },
    {
      "name": "J1",
      "amplitude": 0.130865,
      "phase_UTC": 30.826519
    },
    {
      "name": "L2",
      "amplitude": 0.485242,
      "phase_UTC": -173.182182
    },
    {
      "name": "R2",
      "amplitude": 0.057683,
      "phase_UTC": 95.098112
    },
    {
      "name": "2Q1",
      "amplitude": 0.148965,
      "phase_UTC": -5.949116
    },
    {
      "name": "MSF",
      "amplitude": 0.245263,
      "phase_UTC": 118.371617
    },
    {
      "name": "MSQM",
      "amplitude": 0.114148,
      "phase_UTC": 134.911567
    },
    {
      "name": "EP2",
      "amplitude": 0.465131,
      "phase_UTC": 132.509205
    },
    {
      "name": "M3",
      "amplitude": 0.449034,
      "phase_UTC": 13.421418
    },
    {
      "name": "MU2",
      "amplitude": 1.740391,
      "phase_UTC": 140.944822
    },
    {
      "name": "MTM",
      "amplitude": 0.037527,
      "phase_UTC": -108.972156
    },
    {
      "name": "NU2",
      "amplitude": 1.947832,
      "phase_UTC": 166.979027
    },
    {
      "name": "LAMBDA2",
      "amplitude": 0.127295,
      "phase_UTC": -110.110752
    },
    {
      "name": "MN4",
      "amplitude": 0.132341,
      "phase_UTC": -22.791521
    },
    {
      "name": "MS4",
      "amplitude": 0.078927,
      "phase_UTC": 156.429515
    },
    {
      "name": "MKS2",
      "amplitude": 0.776793,
      "phase_UTC": -170.018807
    },
    {
      "name": "N4",
      "amplitude": 0.120507,
      "phase_UTC": 42.879509
    },
    {
      "name": "M6",
      "amplitude": 0.061866,
      "phase_UTC": -154.625314
    },
    {
      "name": "M8",
      "amplitude": 0.101527,
      "phase_UTC": -174.104798
    },
    {
      "name": "S4",
      "amplitude": 0.119384,
      "phase_UTC": 88.000319
    },
    {
      "name": "OO1",
      "amplitude": 0.209151,
      "phase_UTC": 122.382998
    },
    {
      "name": "S3",
      "amplitude": 0.108978,
      "phase_UTC": -73.089337
    },
    {
      "name": "MA2",
      "amplitude": 0.643044,
      "phase_UTC": 148.645754
    },
    {
      "name": "MB2",
      "amplitude": 0.859366,
      "phase_UTC": 13.064995
    },
    {
      "name": "T3",
      "amplitude": 0.210908,
      "phase_UTC": 145.607731
    },
    {
      "name": "R3",
      "amplitude": 0.256086,
      "phase_UTC": -44.674583
    },
    {
      "name": "RHO1",
      "amplitude": 0.155194,
      "phase_UTC": 13.161808
    },
    {
      "name": "SGM",
      "amplitude": 0.026756,
      "phase_UTC": -118.122774
    },
    {
      "name": "3L2",
      "amplitude": 0.298257,
      "phase_UTC": -88.394612
    },
    {
      "name": "3N2",
      "amplitude": 0.172872,
      "phase_UTC": -1.386077
    },
    {
      "name": "2SM2",
      "amplitude": 0.046659,
      "phase_UTC": -121.421438
    },
    {
      "name": "2MS6",
      "amplitude": 0.160904,
      "phase_UTC": -76.559981
    },
    {
      "name": "2MK5",
      "amplitude": 0.149565,
      "phase_UTC": -111.165798
    },
    {
      "name": "2MO5",
      "amplitude": 0.08388,
      "phase_UTC": 34.36474
    }
  ],
  "secondary_offset": null
}
