{
  "id": "kreekrak-noord-kreekrnd-nld-rws-hist",
  "name": "kreekrak_noord-kreekrnd-nld-rws_hist",
  "continent": "Europe",
  "country": "Netherlands",
  "latitude": 51.450047,
  "longitude": 4.229827,
  "type": "reference",
  "timezone": "Europe/Amsterdam",
  "disclaimers": "Possible quality control issues",
  "source": {
    "name": "TICON-4",
    "url": "https://www.seanoe.org/data/00980/109129/",
    "id": "kreekrak_noord-kreekrnd-nld-rws_hist",
    "datum": "Normal Amsterdam Level",
    "observation_period": {
      "start": "28/02/1975",
      "end": "08/07/2014",
      "years": 40
    }
  },
  "license": {
    "name": "cc-by-4.0",
    "url": "https://creativecommons.org/licenses/by/4.0/"
  },
  "harmonic_constituents": [
    {
      "name": "M2",
      "amplitude": 47.094789,
      "phase_UTC": 68.80942
    },
    {
      "name": "N2",
      "amplitude": 7.356664,
      "phase_UTC": 43.089081
    },
    {
      "name": "S2",
      "amplitude": 11.587654,
      "phase_UTC": 131.461942
    },
    {
      "name": "K2",
      "amplitude": 3.047476,
      "phase_UTC": 132.127009
    },
    {
      "name": "2N2",
      "amplitude": 0.752561,
      "phase_UTC": 19.122605
    },
    {
      "name": "S1",
      "amplitude": 0.317902,
      "phase_UTC": 3.720336
    },
    {
      "name": "K1",
      "amplitude": 1.941945,
      "phase_UTC": 14.820724
    },
    {
      "name": "P1",
      "amplitude": 1.083127,
      "phase_UTC": 2.716999
    },
    {
      "name": "O1",
      "amplitude": 2.711288,
      "phase_UTC": -162.341516
    },
    {
      "name": "Q1",
      "amplitude": 0.976849,
      "phase_UTC": 138.489091
    },
    {
      "name": "M1",
      "amplitude": 0.124375,
      "phase_UTC": -85.578259
    },
    {
      "name": "M4",
      "amplitude": 2.773811,
      "phase_UTC": -165.916937
    },
    {
      "name": "MM",
      "amplitude": 0.406404,
      "phase_UTC": 85.474172
    },
    {
      "name": "MF",
      "amplitude": 0.226366,
      "phase_UTC": 130.207855
    },
    {
      "name": "SA",
      "amplitude": 2.687513,
      "phase_UTC": -107.531164
    },
    {
      "name": "SSA",
      "amplitude": 1.203506,
      "phase_UTC": 153.695387
    },
    {
      "name": "T2",
      "amplitude": 0.451743,
      "phase_UTC": 179.684509
    },
    {
      "name": "J1",
      "amplitude": 0.145356,
      "phase_UTC": 142.862132
    },
    {
      "name": "L2",
      "amplitude": 3.798695,
      "phase_UTC": 86.66829
    },
    {
      "name": "R2",
      "amplitude": 0.531336,
      "phase_UTC": -174.096105
    },
    {
      "name": "2Q1",
      "amplitude": 0.123687,
      "phase_UTC": 87.088514
    },
    {
      "name": "MSF",
      "amplitude": 1.688024,
      "phase_UTC": 44.924784
    },
    {
      "name": "MSQM",
      "amplitude": 0.050493,
      "phase_UTC": 61.391949
    },
    {
      "name": "EP2",
      "amplitude": 1.055014,
      "phase_UTC": 153.391338
    },
    {
      "name": "M3",
      "amplitude": 0.168112,
      "phase_UTC": 179.766645
    },
    {
      "name": "MU2",
      "amplitude": 4.744724,
      "phase_UTC": 170.120271
    },
    {
      "name": "MTM",
      "amplitude": 0.067139,
      "phase_UTC": 171.068345
    },
    {
      "name": "NU2",
      "amplitude": 2.717861,
      "phase_UTC": 32.455513
    },
    {
      "name": "LAMBDA2",
      "amplitude": 1.830573,
      "phase_UTC": 80.479589
    },
    {
      "name": "MN4",
      "amplitude": 0.933148,
      "phase_UTC": 168.237234
    },
    {
      "name": "MS4",
      "amplitude": 1.726143,
      "phase_UTC": -122.899109
    },
    {
      "name": "MKS2",
      "amplitude": 0.613274,
      "phase_UTC": 36.748988
    },
    {
      "name": "N4",
      "amplitude": 0.178683,
      "phase_UTC": 129.757312
    },
    {
      "name": "M6",
      "amplitude": 3.392515,
      "phase_UTC": 170.640987
    },
    {
      "name": "M8",
      "amplitude": 0.179501,
      "phase_UTC": 169.247824
    },
    {
      "name": "S4",
      "amplitude": 0.067051,
      "phase_UTC": -105.97064
    },
    {
      "name": "OO1",
      "amplitude": 0.134133,
      "phase_UTC": 152.88957
    },
    {
      "name": "S3",
      "amplitude": 0.034353,
      "phase_UTC": -151.563915
    },
    {
      "name": "MA2",
      "amplitude": 2.01249,
      "phase_UTC": -78.878825
    },
    {
      "name": "MB2",
      "amplitude": 2.048036,
      "phase_UTC": -154.194794
    },
    {
      "name": "T3",
      "amplitude": 0.094395,
      "phase_UTC": 71.77163
    },
    {
      "name": "R3",
      "amplitude": 0.212026,
      "phase_UTC": -61.586649
    },
    {
      "name": "RHO1",
      "amplitude": 0.189116,
      "phase_UTC": 139.92353
    },
    {
      "name": "SGM",
      "amplitude": 0.098642,
      "phase_UTC": 75.821731
    },
    {
      "name": "3L2",
      "amplitude": 0.570899,
      "phase_UTC": -38.494949
    },
    {
      "name": "3N2",
      "amplitude": 1.358634,
      "phase_UTC": -37.935398
    },
    {
      "name": "2SM2",
      "amplitude": 1.291301,
      "phase_UTC": -1.341606
    },
    {
      "name": "2MS6",
      "amplitude": 3.005326,
      "phase_UTC": -136.741323
    },
    {
      "name": "2MK5",
      "amplitude": 0.042948,
      "phase_UTC": -4.556888
    },
    {
      "name": "2MO5",
      "amplitude": 0.187712,
      "phase_UTC": -21.439466
    }
  ],
  "secondary_offset": null
}
