{
  "id": "rozenburgsesluis-noordzijde-rozbssnzde-nld-rws-hist",
  "name": "rozenburgsesluis_noordzijde-rozbssnzde-nld-rws_hist",
  "continent": "Europe",
  "country": "Netherlands",
  "latitude": 51.895772,
  "longitude": 4.228893,
  "type": "reference",
  "timezone": "Europe/Amsterdam",
  "disclaimers": "No obvious issues",
  "source": {
    "name": "TICON-4",
    "url": "https://www.seanoe.org/data/00980/109129/",
    "id": "rozenburgsesluis_noordzijde-rozbssnzde-nld-rws_hist",
    "datum": "Normal Amsterdam Level",
    "observation_period": {
      "start": "01/01/1972",
      "end": "07/12/1983",
      "years": 13
    }
  },
  "license": {
    "name": "cc-by-4.0",
    "url": "https://creativecommons.org/licenses/by/4.0/"
  },
  "harmonic_constituents": [
    {
      "name": "M2",
      "amplitude": 83.557191,
      "phase_UTC": 57.803508
    },
    {
      "name": "N2",
      "amplitude": 12.341573,
      "phase_UTC": 30.883366
    },
    {
      "name": "S2",
      "amplitude": 20.375801,
      "phase_UTC": 116.64867
    },
    {
      "name": "K2",
      "amplitude": 6.03175,
      "phase_UTC": 117.182112
    },
    {
      "name": "2N2",
      "amplitude": 1.615333,
      "phase_UTC": -0.410288
    },
    {
      "name": "S1",
      "amplitude": 1.049924,
      "phase_UTC": -77.664351
    },
    {
      "name": "K1",
      "amplitude": 7.97078,
      "phase_UTC": -13.498864
    },
    {
      "name": "P1",
      "amplitude": 3.390877,
      "phase_UTC": -26.825096
    },
    {
      "name": "O1",
      "amplitude": 11.301166,
      "phase_UTC": 175.972468
    },
    {
      "name": "Q1",
      "amplitude": 3.849812,
      "phase_UTC": 124.35025
    },
    {
      "name": "M1",
      "amplitude": 0.295068,
      "phase_UTC": -104.741638
    },
    {
      "name": "M4",
      "amplitude": 19.429149,
      "phase_UTC": 102.272669
    },
    {
      "name": "MM",
      "amplitude": 1.603573,
      "phase_UTC": 117.742145
    },
    {
      "name": "MF",
      "amplitude": 1.585707,
      "phase_UTC": 147.880884
    },
    {
      "name": "SA",
      "amplitude": 8.997897,
      "phase_UTC": -144.97126
    },
    {
      "name": "SSA",
      "amplitude": 3.365704,
      "phase_UTC": 143.390041
    },
    {
      "name": "T2",
      "amplitude": 1.404468,
      "phase_UTC": 98.640639
    },
    {
      "name": "J1",
      "amplitude": 0.453928,
      "phase_UTC": 60.117419
    },
    {
      "name": "L2",
      "amplitude": 7.268849,
      "phase_UTC": 82.132489
    },
    {
      "name": "R2",
      "amplitude": 0.180932,
      "phase_UTC": 1.517796
    },
    {
      "name": "2Q1",
      "amplitude": 0.595536,
      "phase_UTC": 57.006483
    },
    {
      "name": "MSF",
      "amplitude": 2.701472,
      "phase_UTC": 45.70804
    },
    {
      "name": "MSQM",
      "amplitude": 0.352329,
      "phase_UTC": -17.659699
    },
    {
      "name": "EP2",
      "amplitude": 1.893662,
      "phase_UTC": 162.508845
    },
    {
      "name": "M3",
      "amplitude": 0.260075,
      "phase_UTC": -112.547889
    },
    {
      "name": "MU2",
      "amplitude": 8.817876,
      "phase_UTC": 178.262564
    },
    {
      "name": "MTM",
      "amplitude": 0.313542,
      "phase_UTC": 173.998408
    },
    {
      "name": "NU2",
      "amplitude": 5.18255,
      "phase_UTC": 26.424132
    },
    {
      "name": "LAMBDA2",
      "amplitude": 3.380846,
      "phase_UTC": 79.965199
    },
    {
      "name": "MN4",
      "amplitude": 6.875722,
      "phase_UTC": 77.382858
    },
    {
      "name": "MS4",
      "amplitude": 12.231701,
      "phase_UTC": 156.757022
    },
    {
      "name": "MKS2",
      "amplitude": 0.915737,
      "phase_UTC": -108.560135
    },
    {
      "name": "N4",
      "amplitude": 1.651139,
      "phase_UTC": 48.38492
    },
    {
      "name": "M6",
      "amplitude": 5.907341,
      "phase_UTC": 48.49679
    },
    {
      "name": "M8",
      "amplitude": 3.393736,
      "phase_UTC": 120.464449
    },
    {
      "name": "S4",
      "amplitude": 1.211652,
      "phase_UTC": -118.766926
    },
    {
      "name": "OO1",
      "amplitude": 0.340368,
      "phase_UTC": 133.16091
    },
    {
      "name": "S3",
      "amplitude": 0.106092,
      "phase_UTC": 9.395425
    },
    {
      "name": "MA2",
      "amplitude": 1.904846,
      "phase_UTC": 49.238642
    },
    {
      "name": "MB2",
      "amplitude": 0.803919,
      "phase_UTC": 92.06895
    },
    {
      "name": "T3",
      "amplitude": 0.144341,
      "phase_UTC": 13.512306
    },
    {
      "name": "R3",
      "amplitude": 0.60051,
      "phase_UTC": -144.6738
    },
    {
      "name": "RHO1",
      "amplitude": 0.759963,
      "phase_UTC": 148.838559
    },
    {
      "name": "SGM",
      "amplitude": 0.228212,
      "phase_UTC": 159.263975
    },
    {
      "name": "3L2",
      "amplitude": 0.398567,
      "phase_UTC": 104.576278
    },
    {
      "name": "3N2",
      "amplitude": 0.250949,
      "phase_UTC": 45.314001
    },
    {
      "name": "2SM2",
      "amplitude": 2.407901,
      "phase_UTC": -7.935272
    },
    {
      "name": "2MS6",
      "amplitude": 5.085286,
      "phase_UTC": 106.359994
    },
    {
      "name": "2MK5",
      "amplitude": 1.802394,
      "phase_UTC": -143.706007
    },
    {
      "name": "2MO5",
      "amplitude": 1.846615,
      "phase_UTC": -127.822898
    }
  ],
  "secondary_offset": null
}
