{
  "id": "ilepossessioncrozettg-60minute-ile-fra-cmems",
  "name": "ilepossessioncrozettg_60minute-ile-fra-cmems",
  "continent": "Europe",
  "country": "France",
  "latitude": -46.425678,
  "longitude": 51.862862,
  "type": "reference",
  "timezone": "Indian/Kerguelen",
  "disclaimers": "Possible datum and quality control issues",
  "source": {
    "name": "TICON-4",
    "url": "https://www.seanoe.org/data/00980/109129/",
    "id": "ilepossessioncrozettg_60minute-ile-fra-cmems",
    "datum": "chart datum",
    "observation_period": {
      "start": "19/11/1995",
      "end": "27/04/2013",
      "years": 14
    }
  },
  "license": {
    "name": "cc-by-4.0",
    "url": "https://creativecommons.org/licenses/by/4.0/"
  },
  "harmonic_constituents": [
    {
      "name": "M2",
      "amplitude": 9.885575,
      "phase_UTC": 157.068189
    },
    {
      "name": "N2",
      "amplitude": 2.084352,
      "phase_UTC": 131.319216
    },
    {
      "name": "S2",
      "amplitude": 2.879875,
      "phase_UTC": -170.245747
    },
    {
      "name": "K2",
      "amplitude": 0.80155,
      "phase_UTC": -165.789912
    },
    {
      "name": "2N2",
      "amplitude": 0.378325,
      "phase_UTC": 111.284866
    },
    {
      "name": "S1",
      "amplitude": 0.283331,
      "phase_UTC": -57.555254
    },
    {
      "name": "K1",
      "amplitude": 1.783784,
      "phase_UTC": 126.204002
    },
    {
      "name": "P1",
      "amplitude": 0.354241,
      "phase_UTC": 131.505051
    },
    {
      "name": "O1",
      "amplitude": 1.647458,
      "phase_UTC": -71.137711
    },
    {
      "name": "Q1",
      "amplitude": 0.561928,
      "phase_UTC": -92.121898
    },
    {
      "name": "M1",
      "amplitude": 0.132214,
      "phase_UTC": 62.332604
    },
    {
      "name": "M4",
      "amplitude": 0.751976,
      "phase_UTC": 176.168022
    },
    {
      "name": "MM",
      "amplitude": 1.702351,
      "phase_UTC": -166.247829
    },
    {
      "name": "MF",
      "amplitude": 1.314547,
      "phase_UTC": -154.628249
    },
    {
      "name": "SA",
      "amplitude": 2.445653,
      "phase_UTC": 103.263707
    },
    {
      "name": "SSA",
      "amplitude": 0.815339,
      "phase_UTC": 166.85606
    },
    {
      "name": "T2",
      "amplitude": 0.311393,
      "phase_UTC": -154.849582
    },
    {
      "name": "J1",
      "amplitude": 0.137297,
      "phase_UTC": 140.388764
    },
    {
      "name": "L2",
      "amplitude": 0.170907,
      "phase_UTC": -162.606572
    },
    {
      "name": "R2",
      "amplitude": 0.091132,
      "phase_UTC": -4.221608
    },
    {
      "name": "2Q1",
      "amplitude": 0.140921,
      "phase_UTC": -113.143783
    },
    {
      "name": "MSF",
      "amplitude": 0.857335,
      "phase_UTC": 167.283545
    },
    {
      "name": "MSQM",
      "amplitude": 0.151368,
      "phase_UTC": -108.699546
    },
    {
      "name": "EP2",
      "amplitude": 0.221089,
      "phase_UTC": 116.202932
    },
    {
      "name": "M3",
      "amplitude": 0.306806,
      "phase_UTC": -35.226361
    },
    {
      "name": "MU2",
      "amplitude": 0.499796,
      "phase_UTC": 131.157458
    },
    {
      "name": "MTM",
      "amplitude": 0.231511,
      "phase_UTC": 175.56325
    },
    {
      "name": "NU2",
      "amplitude": 0.883872,
      "phase_UTC": 143.638392
    },
    {
      "name": "LAMBDA2",
      "amplitude": 0.167291,
      "phase_UTC": -36.700109
    },
    {
      "name": "MN4",
      "amplitude": 0.209663,
      "phase_UTC": 157.84838
    },
    {
      "name": "MS4",
      "amplitude": 0.650038,
      "phase_UTC": -125.207359
    },
    {
      "name": "MKS2",
      "amplitude": 0.177623,
      "phase_UTC": -79.100296
    },
    {
      "name": "N4",
      "amplitude": 0.089937,
      "phase_UTC": 127.368905
    },
    {
      "name": "M6",
      "amplitude": 0.032803,
      "phase_UTC": 160.142233
    },
    {
      "name": "M8",
      "amplitude": 0.036128,
      "phase_UTC": -159.275091
    },
    {
      "name": "S4",
      "amplitude": 0.142679,
      "phase_UTC": -38.35188
    },
    {
      "name": "OO1",
      "amplitude": 0.174713,
      "phase_UTC": 133.290683
    },
    {
      "name": "S3",
      "amplitude": 0.127548,
      "phase_UTC": 54.201876
    },
    {
      "name": "MA2",
      "amplitude": 0.539943,
      "phase_UTC": -170.542518
    },
    {
      "name": "MB2",
      "amplitude": 0.609605,
      "phase_UTC": 110.518816
    },
    {
      "name": "T3",
      "amplitude": 0.1712,
      "phase_UTC": -173.487296
    },
    {
      "name": "R3",
      "amplitude": 0.30184,
      "phase_UTC": 19.110418
    },
    {
      "name": "RHO1",
      "amplitude": 0.157056,
      "phase_UTC": -74.603476
    },
    {
      "name": "SGM",
      "amplitude": 0.115676,
      "phase_UTC": 112.844697
    },
    {
      "name": "3L2",
      "amplitude": 0.353467,
      "phase_UTC": -124.881023
    },
    {
      "name": "3N2",
      "amplitude": 0.975357,
      "phase_UTC": 55.53421
    },
    {
      "name": "2SM2",
      "amplitude": 0.071235,
      "phase_UTC": -154.831198
    },
    {
      "name": "2MS6",
      "amplitude": 0.182003,
      "phase_UTC": -102.855005
    },
    {
      "name": "2MK5",
      "amplitude": 0.087697,
      "phase_UTC": 20.054191
    },
    {
      "name": "2MO5",
      "amplitude": 0.084172,
      "phase_UTC": 87.273014
    }
  ],
  "secondary_offset": null
}
