{
  "id": "ouveatg-60minute-ouv-fra-cmems",
  "name": "ouveatg_60minute-ouv-fra-cmems",
  "continent": "Europe",
  "country": "France",
  "latitude": -20.54982,
  "longitude": 166.56187,
  "type": "reference",
  "timezone": "Pacific/Noumea",
  "disclaimers": "No obvious issues",
  "source": {
    "name": "TICON-4",
    "url": "https://www.seanoe.org/data/00980/109129/",
    "id": "ouveatg_60minute-ouv-fra-cmems",
    "datum": "chart datum",
    "observation_period": {
      "start": "06/04/1981",
      "end": "31/03/2025",
      "years": 17
    }
  },
  "license": {
    "name": "cc-by-4.0",
    "url": "https://creativecommons.org/licenses/by/4.0/"
  },
  "harmonic_constituents": [
    {
      "name": "M2",
      "amplitude": 37.763674,
      "phase_UTC": -144.00016
    },
    {
      "name": "N2",
      "amplitude": 8.364348,
      "phase_UTC": -163.454521
    },
    {
      "name": "S2",
      "amplitude": 9.129258,
      "phase_UTC": -141.175115
    },
    {
      "name": "K2",
      "amplitude": 2.688479,
      "phase_UTC": -147.890957
    },
    {
      "name": "2N2",
      "amplitude": 1.018128,
      "phase_UTC": -178.339279
    },
    {
      "name": "S1",
      "amplitude": 0.305572,
      "phase_UTC": -105.54193
    },
    {
      "name": "K1",
      "amplitude": 15.851155,
      "phase_UTC": 31.610724
    },
    {
      "name": "P1",
      "amplitude": 4.724275,
      "phase_UTC": 27.439855
    },
    {
      "name": "O1",
      "amplitude": 7.998914,
      "phase_UTC": 10.861132
    },
    {
      "name": "Q1",
      "amplitude": 1.291228,
      "phase_UTC": -8.346957
    },
    {
      "name": "M1",
      "amplitude": 0.614936,
      "phase_UTC": -93.700317
    },
    {
      "name": "M4",
      "amplitude": 0.181014,
      "phase_UTC": 168.6617
    },
    {
      "name": "MM",
      "amplitude": 1.026983,
      "phase_UTC": 8.983254
    },
    {
      "name": "MF",
      "amplitude": 0.845262,
      "phase_UTC": 29.194798
    },
    {
      "name": "SA",
      "amplitude": 7.043244,
      "phase_UTC": -49.275271
    },
    {
      "name": "SSA",
      "amplitude": 1.137167,
      "phase_UTC": -20.094183
    },
    {
      "name": "T2",
      "amplitude": 0.436889,
      "phase_UTC": -127.93073
    },
    {
      "name": "J1",
      "amplitude": 0.936044,
      "phase_UTC": 47.22967
    },
    {
      "name": "L2",
      "amplitude": 0.90771,
      "phase_UTC": -132.541972
    },
    {
      "name": "R2",
      "amplitude": 0.11435,
      "phase_UTC": 164.570738
    },
    {
      "name": "2Q1",
      "amplitude": 0.113848,
      "phase_UTC": -42.82129
    },
    {
      "name": "MSF",
      "amplitude": 0.215047,
      "phase_UTC": -38.509786
    },
    {
      "name": "MSQM",
      "amplitude": 0.066663,
      "phase_UTC": -24.863881
    },
    {
      "name": "EP2",
      "amplitude": 0.22407,
      "phase_UTC": 178.225546
    },
    {
      "name": "M3",
      "amplitude": 0.60704,
      "phase_UTC": 154.432359
    },
    {
      "name": "MU2",
      "amplitude": 1.054643,
      "phase_UTC": -175.730902
    },
    {
      "name": "MTM",
      "amplitude": 0.093783,
      "phase_UTC": 113.17032
    },
    {
      "name": "NU2",
      "amplitude": 1.621386,
      "phase_UTC": -162.029935
    },
    {
      "name": "LAMBDA2",
      "amplitude": 0.282344,
      "phase_UTC": -157.061402
    },
    {
      "name": "MN4",
      "amplitude": 0.066754,
      "phase_UTC": 149.142478
    },
    {
      "name": "MS4",
      "amplitude": 0.105773,
      "phase_UTC": -156.595003
    },
    {
      "name": "MKS2",
      "amplitude": 0.015732,
      "phase_UTC": -137.341642
    },
    {
      "name": "N4",
      "amplitude": 0.013476,
      "phase_UTC": 97.624468
    },
    {
      "name": "M6",
      "amplitude": 0.053745,
      "phase_UTC": -47.816825
    },
    {
      "name": "M8",
      "amplitude": 0.012007,
      "phase_UTC": 130.014592
    },
    {
      "name": "S4",
      "amplitude": 0.11388,
      "phase_UTC": -167.345606
    },
    {
      "name": "OO1",
      "amplitude": 0.713061,
      "phase_UTC": 97.188901
    },
    {
      "name": "S3",
      "amplitude": 0.05879,
      "phase_UTC": 179.634099
    },
    {
      "name": "MA2",
      "amplitude": 0.203269,
      "phase_UTC": -155.230845
    },
    {
      "name": "MB2",
      "amplitude": 0.432102,
      "phase_UTC": 137.610595
    },
    {
      "name": "T3",
      "amplitude": 0.182791,
      "phase_UTC": -89.038502
    },
    {
      "name": "R3",
      "amplitude": 0.223662,
      "phase_UTC": 87.329182
    },
    {
      "name": "RHO1",
      "amplitude": 0.264712,
      "phase_UTC": -11.142077
    },
    {
      "name": "SGM",
      "amplitude": 0.125824,
      "phase_UTC": 142.649637
    },
    {
      "name": "3L2",
      "amplitude": 0.386904,
      "phase_UTC": -41.381808
    },
    {
      "name": "3N2",
      "amplitude": 0.357627,
      "phase_UTC": -91.946179
    },
    {
      "name": "2SM2",
      "amplitude": 0.138992,
      "phase_UTC": -18.278835
    },
    {
      "name": "2MS6",
      "amplitude": 0.187122,
      "phase_UTC": -20.623601
    },
    {
      "name": "2MK5",
      "amplitude": 0.058316,
      "phase_UTC": -113.491221
    },
    {
      "name": "2MO5",
      "amplitude": 0.032548,
      "phase_UTC": 116.529184
    }
  ],
  "secondary_offset": null
}
