{
  "id": "us-ny-kingston",
  "name": "Kingston",
  "continent": "North America",
  "country": "United States",
  "region": "NY",
  "type": "subordinate",
  "latitude": 41.9183,
  "longitude": -73.9833,
  "timezone": "America/New_York",
  "source": {
    "name": "US National Oceanic and Atmospheric Administration",
    "id": "8518993",
    "published_harmonics": true,
    "url": "https://tidesandcurrents.noaa.gov/stationhome.html?id=8518993",
    "source_url": "https://api.tidesandcurrents.noaa.gov/mdapi/prod/webapi/stations/8518993.json"
  },
  "license": {
    "type": "public domain",
    "commercial_use": true,
    "url": "https://tidesandcurrents.noaa.gov/disclaimers.html"
  },
  "offsets": {
    "reference": "us-ny-new-york-the-battery",
    "height": {
      "type": "ratio",
      "high": 0.81,
      "low": 0.82
    },
    "time": {
      "high": 320,
      "low": 334
    }
  }
}
